boostmypy/__init__.py
boostmypy/boostmypy.py
boostmypy-0.1.1.dist-info/METADATA
boostmypy-0.1.1.dist-info/WHEEL
boostmypy-0.1.1.dist-info/top_level.txt
boostmypy-0.1.1.dist-info/RECORD
