Metadata-Version: 2.1
Name: boostmypy
Version: 0.1.1
Summary: Coming soon lib
Author-email: Andrew Romanov <romanoffnv@gmail.com>
License: MIT
